Conjugator/__init__.py
Conjugator/deutschCLI.py
Conjugator/frenchCLI.py
Conjugator/fuzzy.py
Conjugator/oschecks.py
Conjugator/Deutschconjugation/__init__.py
Conjugator/Deutschconjugation/__version__.py
Conjugator/Deutschconjugation/conjugator.py
Conjugator/Francaisconjugation/__init__.py
Conjugator/Francaisconjugation/__version__.py
Conjugator/Francaisconjugation/conjugator.py
Conjugator/res/frenchverbs.csv
Conjugator/res/germanverbs.csv
console_conjugator-0.1.4.dist-info/LICENSE
console_conjugator-0.1.4.dist-info/METADATA
console_conjugator-0.1.4.dist-info/WHEEL
console_conjugator-0.1.4.dist-info/entry_points.txt
console_conjugator-0.1.4.dist-info/top_level.txt
console_conjugator-0.1.4.dist-info/RECORD
