Metadata-Version: 2.1
Name: console-conjugator
Version: 0.1.4
Summary: Versatile command line conjugator for german
Home-page: https://github.com/Konjugators/console-conjugator
Author: Konjugators
Author-email: shynn.lawrence@gmail.com
License: UNKNOWN
Platform: UNKNOWN
Classifier: Programming Language :: Python :: 3
Classifier: License :: OSI Approved :: MIT License
Classifier: Operating System :: OS Independent
Classifier: Natural Language :: German
Classifier: Natural Language :: French
Classifier: Environment :: Console :: Curses
Classifier: Topic :: Education
Classifier: Environment :: Console
Requires-Python: >=3.4
